mcp_python_interpreter/__init__.py
mcp_python_interpreter/main.py
mcp_python_interpreter/server.py
mcp_python_interpreter_adk_fork-1.4.dist-info/licenses/LICENSE
mcp_python_interpreter_adk_fork-1.4.dist-info/METADATA
mcp_python_interpreter_adk_fork-1.4.dist-info/WHEEL
mcp_python_interpreter_adk_fork-1.4.dist-info/entry_points.txt
mcp_python_interpreter_adk_fork-1.4.dist-info/top_level.txt
mcp_python_interpreter_adk_fork-1.4.dist-info/RECORD
