Metadata-Version: 2.4
Name: mcp-python-interpreter-adk-fork
Version: 1.4
Summary: MCP server for Python code execution and environment management. A fork of yzfly/mcp-python-interpreter for adk compatibility.
Author-email: luutuankiet <dev@kenluu.org>
Project-URL: Homepage, https://github.com/luutuankiet/mcp-python-interpreter
Project-URL: Bug Tracker, https://github.com/luutuankiet/mcp-python-interpreter/issues
Classifier: Programming Language :: Python :: 3
Classifier: License :: OSI Approved :: MIT License
Classifier: Operating System :: OS Independent
Requires-Python: >=3.10
License-File: LICENSE
Requires-Dist: mcp[cli]>=1.6.0
Dynamic: license-file
